Fountain/__init__.py
Fountain/data.py
Fountain/fountain.py
Fountain/layer.py
Fountain/loss.py
Fountain/plot.py
Fountain/utils.py
scFountain-0.0.7.dist-info/METADATA
scFountain-0.0.7.dist-info/WHEEL
scFountain-0.0.7.dist-info/top_level.txt
scFountain-0.0.7.dist-info/RECORD
